djlint/__init__.py
djlint/__main__.py
djlint/const.py
djlint/helpers.py
djlint/lint.py
djlint/output.py
djlint/reformat.py
djlint/rules.yaml
djlint/settings.py
djlint/src.py
djlint/types.pyi
djlint/formatter/__init__.py
djlint/formatter/attributes.py
djlint/formatter/compress.py
djlint/formatter/condense.py
djlint/formatter/css.py
djlint/formatter/expand.py
djlint/formatter/indent.py
djlint/formatter/js.py
djlint/rules/H025.py
djlint/rules/__init__.py
djlint-1.36.2.dist-info/METADATA
djlint-1.36.2.dist-info/WHEEL
djlint-1.36.2.dist-info/entry_points.txt
djlint-1.36.2.dist-info/licenses/LICENSE
djlint-1.36.2.dist-info/RECORD
