Metadata-Version: 2.3
Name: djlint
Version: 1.36.2
Summary: HTML Template Linter and Formatter
Project-URL: documentation, https://djlint.com
Project-URL: repository, https://github.com/djlint/djLint
Author: Christopher Pickering
Maintainer: Christopher Pickering
Maintainer-email: monosans <hsyqixco@protonmail.com>
License: GPL-3.0-or-later
Classifier: License :: OSI Approved :: GNU General Public License v3 or later (GPLv3+)
Classifier: Natural Language :: English
Classifier: Operating System :: OS Independent
Classifier: Programming Language :: Python
Classifier: Programming Language :: Python :: 3 :: Only
Classifier: Programming Language :: Python :: 3.9
Classifier: Programming Language :: Python :: 3.10
Classifier: Programming Language :: Python :: 3.11
Classifier: Programming Language :: Python :: 3.12
Classifier: Programming Language :: Python :: 3.13
Classifier: Typing :: Typed
Requires-Python: >=3.9
Requires-Dist: click>=8.0.1
Requires-Dist: colorama>=0.4.4
Requires-Dist: cssbeautifier>=1.14.4
Requires-Dist: jsbeautifier>=1.14.4
Requires-Dist: json5>=0.9.11
Requires-Dist: pathspec>=0.12
Requires-Dist: pyyaml>=6
Requires-Dist: regex>=2023
Requires-Dist: tomli>=2.0.1; python_version < '3.11'
Requires-Dist: tqdm>=4.62.2
